AutoGenRC_wisarud/__init__.py
AutoGenRC_wisarud/__main__.py
AutoGenRC_wisarud/__version__.py
AutoGenRC_wisarud/base.py
AutoGenRC_wisarud/cli.py
AutoGenRC_wisarud/exploit_module.py
AutoGenRC_wisarud/nmap_module.py
AutoGenRC_wisarud/rc_module.py
AutoGenRC_wisarud/tempCodeRunnerFile.py
AutoGenRC_wisarud/validate.py
AutoGenRC_wisarud/modules/__init__.py
AutoGenRC_wisarud/modules/post_exploit_manage.py
autogenrc_wisarud-0.0.1.dist-info/METADATA
autogenrc_wisarud-0.0.1.dist-info/WHEEL
autogenrc_wisarud-0.0.1.dist-info/licenses/LICENSE
autogenrc_wisarud-0.0.1.dist-info/RECORD
