Metadata-Version: 2.1
Name: AutoGenRC_wisarud
Version: 0.0.1
Summary: Auto Generate Metasploit Resoucre Script
Project-URL: Homepage, https://github.com/Wisarud2k/Autogen_Resource_Script
Author-email: wisarud <wisarud2k@gmail.com>
License-File: LICENSE
Classifier: License :: OSI Approved :: MIT License
Classifier: Operating System :: OS Independent
Classifier: Programming Language :: Python :: 3
Requires-Python: >=3.10
